[
    {
        "inputs": [
            {
                "internalType": "address",
                "name": "_executor",
                "type": "address"
            }
        ],
        "stateMutability": "nonpayable",
        "type": "constructor"
    },
    {
        "inputs": [],
        "name": "WETH",
        "outputs": [
            {
                "internalType": "contract IWETH",
                "name": "",
                "type": "address"
            }
        ],
        "stateMutability": "view",
        "type": "function"
    },
    {
        "inputs": [
            {
                "internalType": "uint256",
                "name": "_amountIn",
                "type": "uint256"
            },
            {
                "internalType": "address[]",
                "name": "_targets",
                "type": "address[]"
            },
            {
                "internalType": "uint256[2][]",
                "name": "_amountsOut",
                "type": "uint256[2][]"
            }
        ],
        "name": "hi",
        "outputs": [],
        "stateMutability": "nonpayable",
        "type": "function"
    },
    {
        "inputs": [
            {
                "internalType": "contract IERC20",
                "name": "token",
                "type": "address"
            },
            {
                "internalType": "address",
                "name": "_to",
                "type": "address"
            },
            {
                "internalType": "uint256",
                "name": "_amount",
                "type": "uint256"
            }
        ],
        "name": "s",
        "outputs": [],
        "stateMutability": "nonpayable",
        "type": "function"
    },
    {
        "inputs": [
            {
                "internalType": "address",
                "name": "_new",
                "type": "address"
            }
        ],
        "name": "setWeth",
        "outputs": [],
        "stateMutability": "nonpayable",
        "type": "function"
    }
]