[
    {
        "inputs": [
            {
                "internalType": "address",
                "name": "_affiliate",
                "type": "address"
            },
            {
                "internalType": "uint256",
                "name": "_hysteresis",
                "type": "uint256"
            },
            {
                "internalType": "address",
                "name": "_uniswapV3Factory",
                "type": "address"
            },
            {
                "internalType": "address",
                "name": "_ichiVaultsFactory",
                "type": "address"
            },
            {
                "internalType": "address",
                "name": "_defaultVaultOwner",
                "type": "address"
            }
        ],
        "stateMutability": "nonpayable",
        "type": "constructor"
    },
    {
        "anonymous": false,
        "inputs": [
            {
                "indexed": true,
                "internalType": "address",
                "name": "affiliate",
                "type": "address"
            }
        ],
        "name": "AffiliateUpdated",
        "type": "event"
    },
    {
        "anonymous": false,
        "inputs": [
            {
                "indexed": true,
                "internalType": "address",
                "name": "defaultVaultOwner",
                "type": "address"
            }
        ],
        "name": "DefaultVaultOwnerUpdated",
        "type": "event"
    },
    {
        "anonymous": false,
        "inputs": [
            {
                "indexed": false,
                "internalType": "uint256",
                "name": "hysteresis",
                "type": "uint256"
            }
        ],
        "name": "HysteresisUpdated",
        "type": "event"
    },
    {
        "anonymous": false,
        "inputs": [
            {
                "indexed": true,
                "internalType": "address",
                "name": "previousOwner",
                "type": "address"
            },
            {
                "indexed": true,
                "internalType": "address",
                "name": "newOwner",
                "type": "address"
            }
        ],
        "name": "OwnershipTransferred",
        "type": "event"
    },
    {
        "anonymous": false,
        "inputs": [
            {
                "indexed": true,
                "internalType": "address",
                "name": "vault",
                "type": "address"
            }
        ],
        "name": "VaultCreated",
        "type": "event"
    },
    {
        "inputs": [],
        "name": "affiliate",
        "outputs": [
            {
                "internalType": "address",
                "name": "",
                "type": "address"
            }
        ],
        "stateMutability": "view",
        "type": "function"
    },
    {
        "inputs": [
            {
                "internalType": "address",
                "name": "depositToken",
                "type": "address"
            },
            {
                "internalType": "address",
                "name": "quoteToken",
                "type": "address"
            },
            {
                "internalType": "uint24",
                "name": "fee",
                "type": "uint24"
            },
            {
                "internalType": "uint16",
                "name": "minObservations",
                "type": "uint16"
            }
        ],
        "name": "createVault",
        "outputs": [
            {
                "internalType": "address",
                "name": "vault",
                "type": "address"
            }
        ],
        "stateMutability": "nonpayable",
        "type": "function"
    },
    {
        "inputs": [],
        "name": "defaultVaultOwner",
        "outputs": [
            {
                "internalType": "address",
                "name": "",
                "type": "address"
            }
        ],
        "stateMutability": "view",
        "type": "function"
    },
    {
        "inputs": [],
        "name": "hysteresis",
        "outputs": [
            {
                "internalType": "uint256",
                "name": "",
                "type": "uint256"
            }
        ],
        "stateMutability": "view",
        "type": "function"
    },
    {
        "inputs": [],
        "name": "ichiVaultsFactory",
        "outputs": [
            {
                "internalType": "address",
                "name": "",
                "type": "address"
            }
        ],
        "stateMutability": "view",
        "type": "function"
    },
    {
        "inputs": [],
        "name": "owner",
        "outputs": [
            {
                "internalType": "address",
                "name": "",
                "type": "address"
            }
        ],
        "stateMutability": "view",
        "type": "function"
    },
    {
        "inputs": [],
        "name": "renounceOwnership",
        "outputs": [],
        "stateMutability": "nonpayable",
        "type": "function"
    },
    {
        "inputs": [
            {
                "internalType": "address",
                "name": "_affiliate",
                "type": "address"
            }
        ],
        "name": "setAffiliate",
        "outputs": [],
        "stateMutability": "nonpayable",
        "type": "function"
    },
    {
        "inputs": [
            {
                "internalType": "address",
                "name": "_defaultVaultOwner",
                "type": "address"
            }
        ],
        "name": "setDefaultVaultOwner",
        "outputs": [],
        "stateMutability": "nonpayable",
        "type": "function"
    },
    {
        "inputs": [
            {
                "internalType": "uint256",
                "name": "_hysteresis",
                "type": "uint256"
            }
        ],
        "name": "setHysteresis",
        "outputs": [],
        "stateMutability": "nonpayable",
        "type": "function"
    },
    {
        "inputs": [
            {
                "internalType": "address",
                "name": "newOwner",
                "type": "address"
            }
        ],
        "name": "transferOwnership",
        "outputs": [],
        "stateMutability": "nonpayable",
        "type": "function"
    },
    {
        "inputs": [],
        "name": "uniswapV3Factory",
        "outputs": [
            {
                "internalType": "address",
                "name": "",
                "type": "address"
            }
        ],
        "stateMutability": "view",
        "type": "function"
    }
]