[
    {
        "inputs": [
            {
                "internalType": "address",
                "name": "taskManager",
                "type": "address"
            },
            {
                "internalType": "string",
                "name": "detailsURI",
                "type": "string"
            },
            {
                "internalType": "address[]",
                "name": "admins",
                "type": "address[]"
            },
            {
                "internalType": "address[]",
                "name": "tokenManagers",
                "type": "address[]"
            },
            {
                "internalType": "address[]",
                "name": "vaultAdmins",
                "type": "address[]"
            },
            {
                "internalType": "address[]",
                "name": "diamondAdmins",
                "type": "address[]"
            }
        ],
        "stateMutability": "nonpayable",
        "type": "constructor"
    },
    {
        "stateMutability": "payable",
        "type": "fallback"
    },
    {
        "inputs": [
            {
                "internalType": "string[]",
                "name": "funcSigs",
                "type": "string[]"
            },
            {
                "internalType": "address[]",
                "name": "facets",
                "type": "address[]"
            }
        ],
        "name": "addFuncs",
        "outputs": [],
        "stateMutability": "nonpayable",
        "type": "function"
    },
    {
        "inputs": [],
        "name": "getDetailsURI",
        "outputs": [
            {
                "internalType": "string",
                "name": "",
                "type": "string"
            }
        ],
        "stateMutability": "view",
        "type": "function"
    },
    {
        "inputs": [
            {
                "internalType": "address",
                "name": "facet",
                "type": "address"
            }
        ],
        "name": "getFacetFuncs",
        "outputs": [
            {
                "internalType": "string[]",
                "name": "",
                "type": "string[]"
            }
        ],
        "stateMutability": "view",
        "type": "function"
    },
    {
        "inputs": [],
        "name": "getFuncs",
        "outputs": [
            {
                "internalType": "string[]",
                "name": "",
                "type": "string[]"
            },
            {
                "internalType": "address[]",
                "name": "",
                "type": "address[]"
            }
        ],
        "stateMutability": "view",
        "type": "function"
    },
    {
        "inputs": [],
        "name": "getTaskManager",
        "outputs": [
            {
                "internalType": "address",
                "name": "",
                "type": "address"
            }
        ],
        "stateMutability": "view",
        "type": "function"
    },
    {
        "inputs": [
            {
                "internalType": "uint256",
                "name": "taskId",
                "type": "uint256"
            },
            {
                "internalType": "address",
                "name": "account",
                "type": "address"
            },
            {
                "internalType": "uint256",
                "name": "role",
                "type": "uint256"
            }
        ],
        "name": "grantRole",
        "outputs": [],
        "stateMutability": "nonpayable",
        "type": "function"
    },
    {
        "inputs": [
            {
                "internalType": "address",
                "name": "account",
                "type": "address"
            },
            {
                "internalType": "uint256",
                "name": "role",
                "type": "uint256"
            }
        ],
        "name": "hasRole",
        "outputs": [
            {
                "internalType": "bool",
                "name": "",
                "type": "bool"
            }
        ],
        "stateMutability": "view",
        "type": "function"
    },
    {
        "inputs": [
            {
                "internalType": "bytes4",
                "name": "interfaceId",
                "type": "bytes4"
            }
        ],
        "name": "isInterfaceIdSuppressed",
        "outputs": [
            {
                "internalType": "bool",
                "name": "",
                "type": "bool"
            }
        ],
        "stateMutability": "view",
        "type": "function"
    },
    {
        "inputs": [
            {
                "internalType": "string[]",
                "name": "funcSigs",
                "type": "string[]"
            }
        ],
        "name": "removeFuncs",
        "outputs": [],
        "stateMutability": "nonpayable",
        "type": "function"
    },
    {
        "inputs": [
            {
                "internalType": "uint256",
                "name": "taskId",
                "type": "uint256"
            },
            {
                "internalType": "address",
                "name": "account",
                "type": "address"
            },
            {
                "internalType": "uint256",
                "name": "role",
                "type": "uint256"
            }
        ],
        "name": "revokeRole",
        "outputs": [],
        "stateMutability": "nonpayable",
        "type": "function"
    },
    {
        "inputs": [
            {
                "internalType": "string",
                "name": "newValue",
                "type": "string"
            }
        ],
        "name": "setDetailsURI",
        "outputs": [],
        "stateMutability": "nonpayable",
        "type": "function"
    },
    {
        "inputs": [
            {
                "internalType": "uint256",
                "name": "adminTaskId",
                "type": "uint256"
            },
            {
                "internalType": "address",
                "name": "newTaskManager",
                "type": "address"
            }
        ],
        "name": "setTaskManager",
        "outputs": [],
        "stateMutability": "nonpayable",
        "type": "function"
    },
    {
        "inputs": [
            {
                "internalType": "bytes4",
                "name": "interfaceId",
                "type": "bytes4"
            }
        ],
        "name": "supportsInterface",
        "outputs": [
            {
                "internalType": "bool",
                "name": "",
                "type": "bool"
            }
        ],
        "stateMutability": "view",
        "type": "function"
    },
    {
        "inputs": [
            {
                "internalType": "bytes4",
                "name": "interfaceId",
                "type": "bytes4"
            },
            {
                "internalType": "bool",
                "name": "suppress",
                "type": "bool"
            }
        ],
        "name": "suppressInterfaceId",
        "outputs": [],
        "stateMutability": "nonpayable",
        "type": "function"
    },
    {
        "stateMutability": "payable",
        "type": "receive"
    }
]