[
    {
        "inputs": [],
        "name": "ERC1820_REGISTRY",
        "outputs": [
            {
                "internalType": "contract IERC1820Registry",
                "name": "",
                "type": "address"
            }
        ],
        "stateMutability": "view",
        "type": "function"
    },
    {
        "inputs": [
            {
                "internalType": "bytes32",
                "name": "interfaceHash",
                "type": "bytes32"
            },
            {
                "internalType": "address",
                "name": "account",
                "type": "address"
            }
        ],
        "name": "canImplementInterfaceForAddress",
        "outputs": [
            {
                "internalType": "bytes32",
                "name": "",
                "type": "bytes32"
            }
        ],
        "stateMutability": "view",
        "type": "function"
    },
    {
        "inputs": [
            {
                "internalType": "address",
                "name": "operator",
                "type": "address"
            },
            {
                "internalType": "address",
                "name": "from",
                "type": "address"
            },
            {
                "internalType": "address",
                "name": "to",
                "type": "address"
            },
            {
                "internalType": "uint256",
                "name": "amount",
                "type": "uint256"
            },
            {
                "internalType": "bytes",
                "name": "userData",
                "type": "bytes"
            },
            {
                "internalType": "bytes",
                "name": "operatorData",
                "type": "bytes"
            }
        ],
        "name": "tokensReceived",
        "outputs": [],
        "stateMutability": "nonpayable",
        "type": "function"
    }
]