[
    {
        "inputs": [
            {
                "internalType": "address",
                "name": "_find",
                "type": "address"
            },
            {
                "internalType": "address",
                "name": "_weth",
                "type": "address"
            },
            {
                "internalType": "address",
                "name": "_earn",
                "type": "address"
            },
            {
                "internalType": "address",
                "name": "_findnft",
                "type": "address"
            },
            {
                "internalType": "address",
                "name": "_mortgage",
                "type": "address"
            },
            {
                "internalType": "address",
                "name": "_mortgagePoolFactory",
                "type": "address"
            },
            {
                "internalType": "address",
                "name": "_math",
                "type": "address"
            },
            {
                "internalType": "address",
                "name": "_signatureAddress",
                "type": "address"
            }
        ],
        "stateMutability": "nonpayable",
        "type": "constructor"
    },
    {
        "anonymous": false,
        "inputs": [
            {
                "indexed": false,
                "internalType": "uint24",
                "name": "cnftPercent",
                "type": "uint24"
            },
            {
                "indexed": false,
                "internalType": "uint24",
                "name": "onftPercent",
                "type": "uint24"
            }
        ],
        "name": "AddNFTPercentConfig",
        "type": "event"
    },
    {
        "anonymous": false,
        "inputs": [
            {
                "components": [
                    {
                        "internalType": "uint24",
                        "name": "fee",
                        "type": "uint24"
                    },
                    {
                        "components": [
                            {
                                "components": [
                                    {
                                        "internalType": "int24",
                                        "name": "tickLower",
                                        "type": "int24"
                                    },
                                    {
                                        "internalType": "int24",
                                        "name": "tickUpper",
                                        "type": "int24"
                                    },
                                    {
                                        "internalType": "uint256",
                                        "name": "amount",
                                        "type": "uint256"
                                    }
                                ],
                                "internalType": "struct UniswapStruct.Position[]",
                                "name": "positions",
                                "type": "tuple[]"
                            },
                            {
                                "internalType": "uint160",
                                "name": "initSqrtPriceX96",
                                "type": "uint160"
                            }
                        ],
                        "internalType": "struct Factory.OspPoolConfigPool",
                        "name": "ospFindPool",
                        "type": "tuple"
                    },
                    {
                        "components": [
                            {
                                "components": [
                                    {
                                        "internalType": "int24",
                                        "name": "tickLower",
                                        "type": "int24"
                                    },
                                    {
                                        "internalType": "int24",
                                        "name": "tickUpper",
                                        "type": "int24"
                                    },
                                    {
                                        "internalType": "uint256",
                                        "name": "amount",
                                        "type": "uint256"
                                    }
                                ],
                                "internalType": "struct UniswapStruct.Position[]",
                                "name": "positions",
                                "type": "tuple[]"
                            },
                            {
                                "internalType": "uint160",
                                "name": "initSqrtPriceX96",
                                "type": "uint160"
                            }
                        ],
                        "internalType": "struct Factory.OspPoolConfigPool",
                        "name": "findOspPool",
                        "type": "tuple"
                    }
                ],
                "indexed": false,
                "internalType": "struct Factory.OspPoolConfigParams",
                "name": "config",
                "type": "tuple"
            }
        ],
        "name": "AddOspPoolConfig",
        "type": "event"
    },
    {
        "anonymous": false,
        "inputs": [
            {
                "components": [
                    {
                        "components": [
                            {
                                "internalType": "string",
                                "name": "name",
                                "type": "string"
                            },
                            {
                                "internalType": "string",
                                "name": "symbol",
                                "type": "string"
                            },
                            {
                                "internalType": "string",
                                "name": "projectId",
                                "type": "string"
                            },
                            {
                                "internalType": "uint256",
                                "name": "stars",
                                "type": "uint256"
                            },
                            {
                                "internalType": "uint256",
                                "name": "poolConfigIndex",
                                "type": "uint256"
                            },
                            {
                                "internalType": "uint256",
                                "name": "nftPercentConfigIndex",
                                "type": "uint256"
                            }
                        ],
                        "internalType": "struct Factory.CreateOSPBaseParams",
                        "name": "base",
                        "type": "tuple"
                    },
                    {
                        "internalType": "uint256",
                        "name": "deadline",
                        "type": "uint256"
                    },
                    {
                        "internalType": "uint256",
                        "name": "buyNFTTokenAmountMax",
                        "type": "uint256"
                    },
                    {
                        "internalType": "uint256",
                        "name": "buyNFTFindAmount",
                        "type": "uint256"
                    },
                    {
                        "internalType": "bytes",
                        "name": "tokenToFindOutPath",
                        "type": "bytes"
                    },
                    {
                        "internalType": "bytes",
                        "name": "signature",
                        "type": "bytes"
                    }
                ],
                "indexed": false,
                "internalType": "struct Factory.CreateOSPParams",
                "name": "params",
                "type": "tuple"
            }
        ],
        "name": "CreateOSP",
        "type": "event"
    },
    {
        "anonymous": false,
        "inputs": [
            {
                "components": [
                    {
                        "components": [
                            {
                                "internalType": "string",
                                "name": "name",
                                "type": "string"
                            },
                            {
                                "internalType": "string",
                                "name": "symbol",
                                "type": "string"
                            },
                            {
                                "internalType": "string",
                                "name": "projectId",
                                "type": "string"
                            },
                            {
                                "internalType": "uint256",
                                "name": "stars",
                                "type": "uint256"
                            },
                            {
                                "internalType": "uint256",
                                "name": "poolConfigIndex",
                                "type": "uint256"
                            },
                            {
                                "internalType": "uint256",
                                "name": "nftPercentConfigIndex",
                                "type": "uint256"
                            }
                        ],
                        "internalType": "struct Factory.CreateOSPBaseParams",
                        "name": "base",
                        "type": "tuple"
                    },
                    {
                        "internalType": "uint256",
                        "name": "deadline",
                        "type": "uint256"
                    },
                    {
                        "internalType": "uint256",
                        "name": "buyNFTTokenAmountMax",
                        "type": "uint256"
                    },
                    {
                        "internalType": "uint256",
                        "name": "buyNFTFindAmount",
                        "type": "uint256"
                    },
                    {
                        "internalType": "bytes",
                        "name": "tokenToFindOutPath",
                        "type": "bytes"
                    },
                    {
                        "internalType": "bytes",
                        "name": "signature",
                        "type": "bytes"
                    }
                ],
                "indexed": false,
                "internalType": "struct Factory.CreateOSPParams",
                "name": "params",
                "type": "tuple"
            },
            {
                "indexed": false,
                "internalType": "uint256",
                "name": "tokenId",
                "type": "uint256"
            }
        ],
        "name": "CreateOSPAndMultiply",
        "type": "event"
    },
    {
        "anonymous": false,
        "inputs": [
            {
                "components": [
                    {
                        "components": [
                            {
                                "internalType": "string",
                                "name": "name",
                                "type": "string"
                            },
                            {
                                "internalType": "string",
                                "name": "symbol",
                                "type": "string"
                            },
                            {
                                "internalType": "string",
                                "name": "projectId",
                                "type": "string"
                            },
                            {
                                "internalType": "uint256",
                                "name": "stars",
                                "type": "uint256"
                            },
                            {
                                "internalType": "uint256",
                                "name": "poolConfigIndex",
                                "type": "uint256"
                            },
                            {
                                "internalType": "uint256",
                                "name": "nftPercentConfigIndex",
                                "type": "uint256"
                            }
                        ],
                        "internalType": "struct Factory.CreateOSPBaseParams",
                        "name": "base",
                        "type": "tuple"
                    },
                    {
                        "internalType": "uint256",
                        "name": "deadline",
                        "type": "uint256"
                    },
                    {
                        "internalType": "bytes",
                        "name": "signature",
                        "type": "bytes"
                    }
                ],
                "indexed": false,
                "internalType": "struct Factory.CreateOSPByProjectOwnerParams",
                "name": "params",
                "type": "tuple"
            }
        ],
        "name": "CreateOSPByProjectOwner",
        "type": "event"
    },
    {
        "anonymous": false,
        "inputs": [
            {
                "components": [
                    {
                        "components": [
                            {
                                "internalType": "string",
                                "name": "name",
                                "type": "string"
                            },
                            {
                                "internalType": "string",
                                "name": "symbol",
                                "type": "string"
                            },
                            {
                                "internalType": "string",
                                "name": "projectId",
                                "type": "string"
                            },
                            {
                                "internalType": "uint256",
                                "name": "stars",
                                "type": "uint256"
                            },
                            {
                                "internalType": "uint256",
                                "name": "poolConfigIndex",
                                "type": "uint256"
                            },
                            {
                                "internalType": "uint256",
                                "name": "nftPercentConfigIndex",
                                "type": "uint256"
                            }
                        ],
                        "internalType": "struct Factory.CreateOSPBaseParams",
                        "name": "base",
                        "type": "tuple"
                    },
                    {
                        "internalType": "uint256",
                        "name": "deadline",
                        "type": "uint256"
                    },
                    {
                        "internalType": "bytes",
                        "name": "signature",
                        "type": "bytes"
                    }
                ],
                "indexed": false,
                "internalType": "struct Factory.CreateOSPByProjectOwnerParams",
                "name": "params",
                "type": "tuple"
            },
            {
                "indexed": false,
                "internalType": "uint256",
                "name": "tokenId",
                "type": "uint256"
            }
        ],
        "name": "CreateOSPByProjectOwnerAndMultiply",
        "type": "event"
    },
    {
        "anonymous": false,
        "inputs": [],
        "name": "DisableSetSignatureAddress",
        "type": "event"
    },
    {
        "anonymous": false,
        "inputs": [
            {
                "indexed": true,
                "internalType": "address",
                "name": "previousOwner",
                "type": "address"
            },
            {
                "indexed": true,
                "internalType": "address",
                "name": "newOwner",
                "type": "address"
            }
        ],
        "name": "OwnershipTransferred",
        "type": "event"
    },
    {
        "anonymous": false,
        "inputs": [
            {
                "indexed": false,
                "internalType": "address",
                "name": "signatureAddress",
                "type": "address"
            }
        ],
        "name": "SetSignatureAddress",
        "type": "event"
    },
    {
        "inputs": [
            {
                "internalType": "uint24",
                "name": "_cnftPercent",
                "type": "uint24"
            },
            {
                "internalType": "uint24",
                "name": "_onftPercent",
                "type": "uint24"
            }
        ],
        "name": "addNFTPercentConfig",
        "outputs": [],
        "stateMutability": "nonpayable",
        "type": "function"
    },
    {
        "inputs": [
            {
                "components": [
                    {
                        "internalType": "uint24",
                        "name": "fee",
                        "type": "uint24"
                    },
                    {
                        "components": [
                            {
                                "components": [
                                    {
                                        "internalType": "int24",
                                        "name": "tickLower",
                                        "type": "int24"
                                    },
                                    {
                                        "internalType": "int24",
                                        "name": "tickUpper",
                                        "type": "int24"
                                    },
                                    {
                                        "internalType": "uint256",
                                        "name": "amount",
                                        "type": "uint256"
                                    }
                                ],
                                "internalType": "struct UniswapStruct.Position[]",
                                "name": "positions",
                                "type": "tuple[]"
                            },
                            {
                                "internalType": "uint160",
                                "name": "initSqrtPriceX96",
                                "type": "uint160"
                            }
                        ],
                        "internalType": "struct Factory.OspPoolConfigPool",
                        "name": "ospFindPool",
                        "type": "tuple"
                    },
                    {
                        "components": [
                            {
                                "components": [
                                    {
                                        "internalType": "int24",
                                        "name": "tickLower",
                                        "type": "int24"
                                    },
                                    {
                                        "internalType": "int24",
                                        "name": "tickUpper",
                                        "type": "int24"
                                    },
                                    {
                                        "internalType": "uint256",
                                        "name": "amount",
                                        "type": "uint256"
                                    }
                                ],
                                "internalType": "struct UniswapStruct.Position[]",
                                "name": "positions",
                                "type": "tuple[]"
                            },
                            {
                                "internalType": "uint160",
                                "name": "initSqrtPriceX96",
                                "type": "uint160"
                            }
                        ],
                        "internalType": "struct Factory.OspPoolConfigPool",
                        "name": "findOspPool",
                        "type": "tuple"
                    }
                ],
                "internalType": "struct Factory.OspPoolConfigParams",
                "name": "config",
                "type": "tuple"
            }
        ],
        "name": "addOspPoolConfig",
        "outputs": [],
        "stateMutability": "nonpayable",
        "type": "function"
    },
    {
        "inputs": [],
        "name": "createFindUniswapPool",
        "outputs": [],
        "stateMutability": "nonpayable",
        "type": "function"
    },
    {
        "inputs": [
            {
                "components": [
                    {
                        "components": [
                            {
                                "internalType": "string",
                                "name": "name",
                                "type": "string"
                            },
                            {
                                "internalType": "string",
                                "name": "symbol",
                                "type": "string"
                            },
                            {
                                "internalType": "string",
                                "name": "projectId",
                                "type": "string"
                            },
                            {
                                "internalType": "uint256",
                                "name": "stars",
                                "type": "uint256"
                            },
                            {
                                "internalType": "uint256",
                                "name": "poolConfigIndex",
                                "type": "uint256"
                            },
                            {
                                "internalType": "uint256",
                                "name": "nftPercentConfigIndex",
                                "type": "uint256"
                            }
                        ],
                        "internalType": "struct Factory.CreateOSPBaseParams",
                        "name": "base",
                        "type": "tuple"
                    },
                    {
                        "internalType": "uint256",
                        "name": "deadline",
                        "type": "uint256"
                    },
                    {
                        "internalType": "uint256",
                        "name": "buyNFTTokenAmountMax",
                        "type": "uint256"
                    },
                    {
                        "internalType": "uint256",
                        "name": "buyNFTFindAmount",
                        "type": "uint256"
                    },
                    {
                        "internalType": "bytes",
                        "name": "tokenToFindOutPath",
                        "type": "bytes"
                    },
                    {
                        "internalType": "bytes",
                        "name": "signature",
                        "type": "bytes"
                    }
                ],
                "internalType": "struct Factory.CreateOSPParams",
                "name": "params",
                "type": "tuple"
            }
        ],
        "name": "createOSP",
        "outputs": [
            {
                "internalType": "uint256",
                "name": "nftNeedPay",
                "type": "uint256"
            },
            {
                "internalType": "address",
                "name": "tokenPay",
                "type": "address"
            }
        ],
        "stateMutability": "payable",
        "type": "function"
    },
    {
        "inputs": [
            {
                "components": [
                    {
                        "components": [
                            {
                                "internalType": "string",
                                "name": "name",
                                "type": "string"
                            },
                            {
                                "internalType": "string",
                                "name": "symbol",
                                "type": "string"
                            },
                            {
                                "internalType": "string",
                                "name": "projectId",
                                "type": "string"
                            },
                            {
                                "internalType": "uint256",
                                "name": "stars",
                                "type": "uint256"
                            },
                            {
                                "internalType": "uint256",
                                "name": "poolConfigIndex",
                                "type": "uint256"
                            },
                            {
                                "internalType": "uint256",
                                "name": "nftPercentConfigIndex",
                                "type": "uint256"
                            }
                        ],
                        "internalType": "struct Factory.CreateOSPBaseParams",
                        "name": "base",
                        "type": "tuple"
                    },
                    {
                        "internalType": "uint256",
                        "name": "deadline",
                        "type": "uint256"
                    },
                    {
                        "internalType": "uint256",
                        "name": "buyNFTTokenAmountMax",
                        "type": "uint256"
                    },
                    {
                        "internalType": "uint256",
                        "name": "buyNFTFindAmount",
                        "type": "uint256"
                    },
                    {
                        "internalType": "bytes",
                        "name": "tokenToFindOutPath",
                        "type": "bytes"
                    },
                    {
                        "internalType": "bytes",
                        "name": "signature",
                        "type": "bytes"
                    }
                ],
                "internalType": "struct Factory.CreateOSPParams",
                "name": "params",
                "type": "tuple"
            },
            {
                "internalType": "uint256",
                "name": "AllFindAmount",
                "type": "uint256"
            },
            {
                "internalType": "uint256",
                "name": "amountPayMax",
                "type": "uint256"
            }
        ],
        "name": "createOSPAndMultiply",
        "outputs": [
            {
                "internalType": "uint256",
                "name": "nftNeedPay",
                "type": "uint256"
            },
            {
                "internalType": "uint256",
                "name": "positionOspAmountDelta",
                "type": "uint256"
            },
            {
                "internalType": "uint256",
                "name": "amountNeedPay",
                "type": "uint256"
            },
            {
                "internalType": "address",
                "name": "tokenPay",
                "type": "address"
            },
            {
                "internalType": "uint256",
                "name": "tokenId",
                "type": "uint256"
            }
        ],
        "stateMutability": "payable",
        "type": "function"
    },
    {
        "inputs": [
            {
                "components": [
                    {
                        "components": [
                            {
                                "internalType": "string",
                                "name": "name",
                                "type": "string"
                            },
                            {
                                "internalType": "string",
                                "name": "symbol",
                                "type": "string"
                            },
                            {
                                "internalType": "string",
                                "name": "projectId",
                                "type": "string"
                            },
                            {
                                "internalType": "uint256",
                                "name": "stars",
                                "type": "uint256"
                            },
                            {
                                "internalType": "uint256",
                                "name": "poolConfigIndex",
                                "type": "uint256"
                            },
                            {
                                "internalType": "uint256",
                                "name": "nftPercentConfigIndex",
                                "type": "uint256"
                            }
                        ],
                        "internalType": "struct Factory.CreateOSPBaseParams",
                        "name": "base",
                        "type": "tuple"
                    },
                    {
                        "internalType": "uint256",
                        "name": "deadline",
                        "type": "uint256"
                    },
                    {
                        "internalType": "bytes",
                        "name": "signature",
                        "type": "bytes"
                    }
                ],
                "internalType": "struct Factory.CreateOSPByProjectOwnerParams",
                "name": "params",
                "type": "tuple"
            }
        ],
        "name": "createOSPByProjectOwner",
        "outputs": [],
        "stateMutability": "nonpayable",
        "type": "function"
    },
    {
        "inputs": [
            {
                "components": [
                    {
                        "components": [
                            {
                                "internalType": "string",
                                "name": "name",
                                "type": "string"
                            },
                            {
                                "internalType": "string",
                                "name": "symbol",
                                "type": "string"
                            },
                            {
                                "internalType": "string",
                                "name": "projectId",
                                "type": "string"
                            },
                            {
                                "internalType": "uint256",
                                "name": "stars",
                                "type": "uint256"
                            },
                            {
                                "internalType": "uint256",
                                "name": "poolConfigIndex",
                                "type": "uint256"
                            },
                            {
                                "internalType": "uint256",
                                "name": "nftPercentConfigIndex",
                                "type": "uint256"
                            }
                        ],
                        "internalType": "struct Factory.CreateOSPBaseParams",
                        "name": "base",
                        "type": "tuple"
                    },
                    {
                        "internalType": "uint256",
                        "name": "deadline",
                        "type": "uint256"
                    },
                    {
                        "internalType": "bytes",
                        "name": "signature",
                        "type": "bytes"
                    }
                ],
                "internalType": "struct Factory.CreateOSPByProjectOwnerParams",
                "name": "params",
                "type": "tuple"
            },
            {
                "internalType": "bytes",
                "name": "tokenToFindOutPath",
                "type": "bytes"
            },
            {
                "internalType": "uint256",
                "name": "AllFindAmount",
                "type": "uint256"
            },
            {
                "internalType": "uint256",
                "name": "amountPayMax",
                "type": "uint256"
            }
        ],
        "name": "createOSPByProjectOwnerAndMultiply",
        "outputs": [
            {
                "internalType": "uint256",
                "name": "positionOspAmountDelta",
                "type": "uint256"
            },
            {
                "internalType": "uint256",
                "name": "amountNeedPay",
                "type": "uint256"
            },
            {
                "internalType": "address",
                "name": "tokenPay",
                "type": "address"
            },
            {
                "internalType": "uint256",
                "name": "tokenId",
                "type": "uint256"
            }
        ],
        "stateMutability": "payable",
        "type": "function"
    },
    {
        "inputs": [],
        "name": "disableSetSignatureAddress",
        "outputs": [],
        "stateMutability": "nonpayable",
        "type": "function"
    },
    {
        "inputs": [],
        "name": "disableSetSignatureAddressFlag",
        "outputs": [
            {
                "internalType": "bool",
                "name": "",
                "type": "bool"
            }
        ],
        "stateMutability": "view",
        "type": "function"
    },
    {
        "inputs": [],
        "name": "earn",
        "outputs": [
            {
                "internalType": "address",
                "name": "",
                "type": "address"
            }
        ],
        "stateMutability": "view",
        "type": "function"
    },
    {
        "inputs": [],
        "name": "findInfo",
        "outputs": [
            {
                "internalType": "address",
                "name": "token",
                "type": "address"
            },
            {
                "internalType": "address",
                "name": "pool",
                "type": "address"
            },
            {
                "internalType": "uint256",
                "name": "cnftTokenId",
                "type": "uint256"
            },
            {
                "internalType": "uint256",
                "name": "onftTokenId",
                "type": "uint256"
            },
            {
                "internalType": "uint24",
                "name": "fee",
                "type": "uint24"
            }
        ],
        "stateMutability": "view",
        "type": "function"
    },
    {
        "inputs": [],
        "name": "findLpTokenIdList",
        "outputs": [
            {
                "internalType": "uint256[]",
                "name": "lpTokenIdList",
                "type": "uint256[]"
            }
        ],
        "stateMutability": "view",
        "type": "function"
    },
    {
        "inputs": [],
        "name": "findnft",
        "outputs": [
            {
                "internalType": "address",
                "name": "",
                "type": "address"
            }
        ],
        "stateMutability": "view",
        "type": "function"
    },
    {
        "inputs": [
            {
                "internalType": "uint256",
                "name": "index",
                "type": "uint256"
            }
        ],
        "name": "getOspPoolConfigs",
        "outputs": [
            {
                "internalType": "uint24",
                "name": "fee",
                "type": "uint24"
            },
            {
                "internalType": "uint160",
                "name": "findOspPoolInitSqrtPriceX96",
                "type": "uint160"
            },
            {
                "components": [
                    {
                        "internalType": "int24",
                        "name": "tickLower",
                        "type": "int24"
                    },
                    {
                        "internalType": "int24",
                        "name": "tickUpper",
                        "type": "int24"
                    },
                    {
                        "internalType": "uint256",
                        "name": "amount",
                        "type": "uint256"
                    }
                ],
                "internalType": "struct UniswapStruct.Position[]",
                "name": "findOspPoolPositions",
                "type": "tuple[]"
            },
            {
                "internalType": "uint160",
                "name": "ospFindPoolInitSqrtPriceX96",
                "type": "uint160"
            },
            {
                "components": [
                    {
                        "internalType": "int24",
                        "name": "tickLower",
                        "type": "int24"
                    },
                    {
                        "internalType": "int24",
                        "name": "tickUpper",
                        "type": "int24"
                    },
                    {
                        "internalType": "uint256",
                        "name": "amount",
                        "type": "uint256"
                    }
                ],
                "internalType": "struct UniswapStruct.Position[]",
                "name": "ospFindPoolPositions",
                "type": "tuple[]"
            },
            {
                "internalType": "uint256",
                "name": "totalSupply",
                "type": "uint256"
            }
        ],
        "stateMutability": "view",
        "type": "function"
    },
    {
        "inputs": [],
        "name": "math",
        "outputs": [
            {
                "internalType": "address",
                "name": "",
                "type": "address"
            }
        ],
        "stateMutability": "view",
        "type": "function"
    },
    {
        "inputs": [],
        "name": "mortgage",
        "outputs": [
            {
                "internalType": "address",
                "name": "",
                "type": "address"
            }
        ],
        "stateMutability": "view",
        "type": "function"
    },
    {
        "inputs": [],
        "name": "mortgagePoolFactory",
        "outputs": [
            {
                "internalType": "address",
                "name": "",
                "type": "address"
            }
        ],
        "stateMutability": "view",
        "type": "function"
    },
    {
        "inputs": [
            {
                "internalType": "uint256",
                "name": "",
                "type": "uint256"
            }
        ],
        "name": "nftPercentConfigs",
        "outputs": [
            {
                "internalType": "uint24",
                "name": "cnft",
                "type": "uint24"
            },
            {
                "internalType": "uint24",
                "name": "onft",
                "type": "uint24"
            }
        ],
        "stateMutability": "view",
        "type": "function"
    },
    {
        "inputs": [
            {
                "internalType": "address",
                "name": "osp",
                "type": "address"
            }
        ],
        "name": "ospLpTokenIdList",
        "outputs": [
            {
                "internalType": "uint256[]",
                "name": "lpTokenIdList",
                "type": "uint256[]"
            }
        ],
        "stateMutability": "view",
        "type": "function"
    },
    {
        "inputs": [],
        "name": "ospPoolConfigsCount",
        "outputs": [
            {
                "internalType": "uint256",
                "name": "",
                "type": "uint256"
            }
        ],
        "stateMutability": "view",
        "type": "function"
    },
    {
        "inputs": [],
        "name": "owner",
        "outputs": [
            {
                "internalType": "address",
                "name": "",
                "type": "address"
            }
        ],
        "stateMutability": "view",
        "type": "function"
    },
    {
        "inputs": [
            {
                "internalType": "string",
                "name": "",
                "type": "string"
            }
        ],
        "name": "projectId2OspToken",
        "outputs": [
            {
                "internalType": "address",
                "name": "",
                "type": "address"
            }
        ],
        "stateMutability": "view",
        "type": "function"
    },
    {
        "inputs": [],
        "name": "renounceOwnership",
        "outputs": [],
        "stateMutability": "nonpayable",
        "type": "function"
    },
    {
        "inputs": [
            {
                "internalType": "address",
                "name": "_signatureAddress",
                "type": "address"
            }
        ],
        "name": "setSignatureAddress",
        "outputs": [],
        "stateMutability": "nonpayable",
        "type": "function"
    },
    {
        "inputs": [],
        "name": "signatureAddress",
        "outputs": [
            {
                "internalType": "address",
                "name": "",
                "type": "address"
            }
        ],
        "stateMutability": "view",
        "type": "function"
    },
    {
        "inputs": [
            {
                "internalType": "address",
                "name": "",
                "type": "address"
            }
        ],
        "name": "token2OspInfo",
        "outputs": [
            {
                "internalType": "uint256",
                "name": "poolConfigIndex",
                "type": "uint256"
            },
            {
                "internalType": "uint256",
                "name": "stars",
                "type": "uint256"
            },
            {
                "internalType": "address",
                "name": "pool",
                "type": "address"
            },
            {
                "internalType": "uint256",
                "name": "cnftTokenId",
                "type": "uint256"
            },
            {
                "internalType": "uint256",
                "name": "onftTokenId",
                "type": "uint256"
            },
            {
                "internalType": "string",
                "name": "projectId",
                "type": "string"
            }
        ],
        "stateMutability": "view",
        "type": "function"
    },
    {
        "inputs": [
            {
                "internalType": "address",
                "name": "newOwner",
                "type": "address"
            }
        ],
        "name": "transferOwnership",
        "outputs": [],
        "stateMutability": "nonpayable",
        "type": "function"
    },
    {
        "inputs": [],
        "name": "weth",
        "outputs": [
            {
                "internalType": "address",
                "name": "",
                "type": "address"
            }
        ],
        "stateMutability": "view",
        "type": "function"
    },
    {
        "stateMutability": "payable",
        "type": "receive"
    }
]